blockchain_simulationTH
