Metadata-Version: 1.1
Name: blockchain-simulationTH
Version: 0.0.2
Summary: (BlockchainTH) Blockchain Simulation by 9Maxxis
Home-page: https://github.com/9Maxxis/blockchain_simulationTH
Author: 9Maxxis
Author-email: UNKNOWN
License: MIT
Download-URL: https://github.com/9Maxxis/blockchain_simulationTH/archive/refs/tags/v0.0.2.zip
Keywords: blockchain,blockchain simulation,9Maxxis
Platform: UNKNOWN
Classifier: Development Status :: 3 - Alpha
Classifier: Intended Audience :: Education
Classifier: Topic :: Software Development :: Build Tools
Classifier: License :: OSI Approved :: MIT License
Classifier: Programming Language :: Python :: 3
Classifier: Programming Language :: Python :: 3.4
Classifier: Programming Language :: Python :: 3.5
Classifier: Programming Language :: Python :: 3.6
Classifier: Programming Language :: Python :: 3.7
Classifier: Programming Language :: Python :: 3.8
Classifier: Programming Language :: Python :: 3.9
Classifier: Programming Language :: Python :: 3.10
